README.md
setup.py
pythontools/__init__.py
pythontools/ansicolors.py
pythontools/autovenv.py
pythontools/env.py
pythontools/gitlab.py
pythontools/init.py
pythontools/loggerutils.py
pythontools/pathutils.py
pythontools.egg-info/PKG-INFO
pythontools.egg-info/SOURCES.txt
pythontools.egg-info/dependency_links.txt
pythontools.egg-info/requires.txt
pythontools.egg-info/top_level.txt