Metadata-Version: 2.1
Name: pythontools
Version: 0.1.1
Summary: Python Tools provides several utility functions and tools that can be used in Python projects.
Home-page: https://gitlab.com/osechet/pythontools
Author: Olivier Sechet
Author-email: osechet@gmail.com
License: MIT
Keywords: developer,tool,utility
Platform: UNKNOWN
Classifier: Development Status :: 3 - Alpha
Classifier: Intended Audience :: Developers
Classifier: Topic :: Software Development :: Build Tools
Classifier: License :: OSI Approved :: MIT License
Classifier: Programming Language :: Python :: 3
Classifier: Programming Language :: Python :: 3.4
Classifier: Programming Language :: Python :: 3 :: Only
Provides-Extra: test
Provides-Extra: dev
